apicache/__init__.py
apicache/cache.py
apicache-0.1.1.dist-info/METADATA
apicache-0.1.1.dist-info/WHEEL
apicache-0.1.1.dist-info/top_level.txt
apicache-0.1.1.dist-info/RECORD
