Metadata-Version: 2.4
Name: apicache
Version: 0.1.1
Summary: A lightweight, data-aware API proxy-cache for reproducible workflows and rate-limit resilience.
Home-page: https://github.com/bayinfosys/apicache
Author: Edward Grundy
Author-email: ed@bayis.co.uk
License: MIT
Classifier: Programming Language :: Python :: 3
Classifier: Operating System :: OS Independent
Requires-Python: >=3.7
Requires-Dist: requests
Dynamic: author
Dynamic: author-email
Dynamic: classifier
Dynamic: description
Dynamic: description-content-type
Dynamic: home-page
Dynamic: license
Dynamic: requires-dist
Dynamic: requires-python
Dynamic: summary
